rustici_software_cloud_v2/__init__.py
rustici_software_cloud_v2/api_client.py
rustici_software_cloud_v2/configuration.py
rustici_software_cloud_v2/rest.py
rustici_software_cloud_v2/api/__init__.py
rustici_software_cloud_v2/api/about_api.py
rustici_software_cloud_v2/api/application_management_api.py
rustici_software_cloud_v2/api/authentication_api.py
rustici_software_cloud_v2/api/content_connectors_api.py
rustici_software_cloud_v2/api/course_api.py
rustici_software_cloud_v2/api/dispatch_api.py
rustici_software_cloud_v2/api/invitations_api.py
rustici_software_cloud_v2/api/learner_api.py
rustici_software_cloud_v2/api/ping_api.py
rustici_software_cloud_v2/api/registration_api.py
rustici_software_cloud_v2/api/reporting_api.py
rustici_software_cloud_v2/api/xapi_api.py
rustici_software_cloud_v2/api/zoomi_api.py
rustici_software_cloud_v2/models/__init__.py
rustici_software_cloud_v2/models/about_schema.py
rustici_software_cloud_v2/models/activity_result_schema.py
rustici_software_cloud_v2/models/application_info_list_schema.py
rustici_software_cloud_v2/models/application_info_schema.py
rustici_software_cloud_v2/models/application_list_schema.py
rustici_software_cloud_v2/models/application_request_schema.py
rustici_software_cloud_v2/models/application_schema.py
rustici_software_cloud_v2/models/application_token.py
rustici_software_cloud_v2/models/asset_file_schema.py
rustici_software_cloud_v2/models/batch_tags_schema.py
rustici_software_cloud_v2/models/comment_schema.py
rustici_software_cloud_v2/models/completion_amount_schema.py
rustici_software_cloud_v2/models/connector_list_schema.py
rustici_software_cloud_v2/models/connector_schema.py
rustici_software_cloud_v2/models/course_activity_schema.py
rustici_software_cloud_v2/models/course_list_non_paged_schema.py
rustici_software_cloud_v2/models/course_list_schema.py
rustici_software_cloud_v2/models/course_reference_schema.py
rustici_software_cloud_v2/models/course_schema.py
rustici_software_cloud_v2-4.0.0.dist-info/LICENSE
rustici_software_cloud_v2-4.0.0.dist-info/METADATA
rustici_software_cloud_v2-4.0.0.dist-info/WHEEL
rustici_software_cloud_v2-4.0.0.dist-info/top_level.txt
rustici_software_cloud_v2-4.0.0.dist-info/RECORD
