Metadata-Version: 2.1
Name: rustici-software-cloud-v2
Version: 4.0.0
Summary: SCORM Cloud Rest API
Home-page: https://github.com/RusticiSoftware/scormcloud-api-v2-client-python
Author-email: systems@rusticisoftware.com
License: UNKNOWN
Keywords: SCORM Cloud Rest API,Rustici Software,SCORM,SCORM Cloud
Platform: UNKNOWN
License-File: LICENSE
Requires-Dist: certifi >=2017.4.17
Requires-Dist: python-dateutil >=2.1
Requires-Dist: six >=1.10
Requires-Dist: urllib3 >=1.23
Requires-Dist: Deprecated >=1.2.13
